update_mypy_hook/__init__.py
update_mypy_hook/__main__.py
update_mypy_hook/py.typed
update_mypy_hook-0.3.0.dist-info/METADATA
update_mypy_hook-0.3.0.dist-info/WHEEL
update_mypy_hook-0.3.0.dist-info/entry_points.txt
update_mypy_hook-0.3.0.dist-info/licenses/license.txt
update_mypy_hook-0.3.0.dist-info/RECORD
