Metadata-Version: 2.4
Name: update-mypy-hook
Version: 0.3.0
Summary: Update the additional dependencies of mypy pre-commit hook from uv.lock
Project-URL: Source, https://github.com/H4rryK4ne/update-mypy-hook
Project-URL: Changes, https://github.com/H4rryK4ne/update-mypy-hook/blob/develop/CHANGELOG.md
Author-email: HarryKane <harrykane@gmx.de>
License-Expression: GPL-3.0-or-later
License-File: license.txt
Classifier: Development Status :: 4 - Beta
Classifier: Environment :: Console
Classifier: Intended Audience :: Developers
Classifier: Programming Language :: Python :: 3 :: Only
Classifier: Topic :: Software Development
Classifier: Typing :: Typed
Requires-Python: >=3.10
Requires-Dist: ruamel-yaml
Requires-Dist: typing-extensions; python_version < '3.11'
Requires-Dist: uv>=0.7.0
